bs4md.py
bootstrap4markdown-0.1.dist-info/LICENSE
bootstrap4markdown-0.1.dist-info/METADATA
bootstrap4markdown-0.1.dist-info/WHEEL
bootstrap4markdown-0.1.dist-info/top_level.txt
bootstrap4markdown-0.1.dist-info/RECORD
