Metadata-Version: 2.1
Name: bootstrap4markdown
Version: 0.1
Summary: A Python-Markdown extension which provides a simple syntax for including Bootstrap objects within a Markdown document.
Author: Waylan Limberg
License: MIT License
Project-URL: repository, https://github.com/waylan/bootstrap4markdown.py
Classifier: Development Status :: 4 - Beta
Classifier: Programming Language :: Python
License-File: LICENSE
Requires-Dist: pymdown-extensions (>=9.10)
